{"$schema":"http://json-schema.org/draft-03/schema","id":"#","type":"object","required":true,"properties":{"cxlb":{"id":"cxlb","type":"array","items":{"id":"0","type":"object","required":true,"properties":{"hbmc":{"pattern":"[一-龥]","id":"hbmc","type":"string","required":true},"sscz":{"pattern":"^[0-9]*\\.[0-9]{2}$","id":"sscz","type":"string","required":true},"zzc":{"pattern":"^[0-9]+\\.[0-9]{2}$","id":"zzc","type":"string","required":true},"hcje":{"pattern":"^[0-9]*\\.[0-9]{2}$","id":"hcje","type":"string","required":true},"zjzh":{"pattern":"^[0-9]+$","id":"zjzh","type":"string","required":true},"ztcz":{"pattern":"^[0-9]*\\.[0-9]{2}$","id":"ztcz","type":"string","required":true},"zjkm":{"pattern":"HGT|FYDJ|SGT","id":"zjkm","type":"string","required":true},"zcky":{"pattern":"^[0-9]*\\.[0-9]{2}$","id":"zcky","type":"string","required":true},"hbdm":{"pattern":"^[0-9]{1,2}$","id":"hbdm","type":"string","required":true},"hrje":{"pattern":"^[0-9]*\\.[0-9]{2}$","id":"hrje","type":"string","required":true},"zjkmsm":{"pattern":"港股通交易二级资金|港股通费用防透支预冻结资金|港股通交易二级资金","id":"zjkmsm","type":"string","required":true},"ztrz":{"pattern":"^[0-9]*\\.[0-9]{2}$","id":"ztrz","type":"string","required":true},"ssrz":{"id":"ssrz","type":"string","required":true}}},"required":true},"cljg":{"id":"cljg","type":"array","items":{"id":"0","type":"object","required":true,"properties":{"code":{"pattern":"MP1B000000","id":"code","type":"string","required":true},"message":{"pattern":"沪港通资金资产查询成功!","id":"message","type":"string","required":true}}},"required":true}}}