{"$schema":"http://json-schema.org/draft-03/schema","id":"#","type":"object","required":true,"properties":{"cxlb":{"id":"cxlb","type":"array","items":{"id":"0","type":"object","required":true,"properties":{"sblxsm":{"pattern":"查询|申报|撤销","id":"sblxsm","type":"string","required":true},"wtzt":{"pattern":"^[A-F]{1}|[0-9]{1}$","id":"wtzt","type":"string","required":true},"sqsl":{"pattern":"^-{0,1}[0-9]+$","id":"sqsl","type":"string","required":true},"ywlsh":{"pattern":"^[0-9]{8}[0-9]*$","id":"ywlsh","type":"string","required":true},"gsxwdm":{"pattern":"^[0-9A-Z]+$","id":"gsxwdm","type":"string","required":true},"fdps":{"id":"fdps","type":"string","required":true},"sblx":{"pattern":"^1$|^2$|^-1$","id":"sblx","type":"string","required":true},"ywlx":{"pattern":"^[A-Z1-9]{1,3}$","id":"ywlx","type":"string","required":true},"fssj":{"pattern":"^[0-9]+$","id":"fssj","type":"string","required":true},"zcps":{"pattern":"^[0-9]+$","id":"zcps","type":"string","required":true},"ggbh":{"pattern":"^[0-9]*$","id":"ggbh","type":"string","required":true},"qqps":{"pattern":"^[0-9]+$","id":"qqps","type":"string","required":true},"yabh":{"pattern":"^[0-9]*$","id":"yabh","type":"string","required":true},"zqdm":{"pattern":"^[0-9]{5}$","id":"zqdm","type":"string","required":true},"fsrq":{"id":"fsrq","type":"string","required":true},"wtztsm":{"pattern":"[一-龥]","id":"wtztsm","type":"string","required":true},"ywlxsm":{"pattern":"[一-龥]","id":"ywlxsm","type":"string","required":true}}},"required":true},"cljg":{"id":"cljg","type":"array","items":{"id":"0","type":"object","required":true,"properties":{"code":{"pattern":"MP1B000000","id":"code","type":"string","required":true},"message":{"pattern":"业务程序运行正常","id":"message","type":"string","required":true}}},"required":true}}}